<?xml version="1.0" encoding="UTF-8"?>
<customUI xmlns="http://schemas.microsoft.com/office/2009/07/customui" onLoad="Ribbon_Load">
  <ribbon>
    <tabs>
      <tab idMso="TabAddIns">
        <group id="MyGroup"
               label="My Group">
            <button id="subscribeButton" label="Subscribe"
                screentip="Get data" onAction="OnSubButton"
                supertip="Get data from channel"/>
            <button id="publishButton" label="Publish"
              screentip="Send data" onAction="OnPubButton"
              supertip="Send data to channel"/>

            <button id="registerButton" label="Register"
              screentip="Register workbook" onAction="OnRegButton"
              supertip="Register workbook with an unique ID"/>
            
        </group>
      </tab>
    </tabs>
  </ribbon>
</customUI>

